{"fetchedAt":1776903044039,"status":200,"body":{"id_player":687735,"kills":19160,"wins":2774,"deaths":7156,"coins":524438,"final_kills":7508,"final_deaths":814,"beds_broken":3100,"played":3514,"winstreak":3,"h_winstreak":59,"level":339,"level_rank":352,"total_players":786103,"current_division":7,"current_division_exp":55960,"past_divisions":"[{\"season_id\": 7, \"division\": 6, \"division_exp\": 68873},{\"season_id\": 6, \"division\": 4, \"division_exp\": 19900},{\"season_id\": 5, \"division\": 2, \"division_exp\": 5395},{\"season_id\": 4, \"division\": 2, \"division_exp\": 1330},{\"season_id\": 3, \"division\": 4, \"division_exp\": 11630},{\"season_id\": 2, \"division\": 2, \"division_exp\": 1060},{\"season_id\": 1, \"division\": 5, \"division_exp\": 26115}]","clan_role":0,"clan_name":"Aetherion","clan_id":32237,"losses":740}}